timetracker/__init__.py
jupyter_timetracker-0.0.3.dist-info/LICENSE
jupyter_timetracker-0.0.3.dist-info/METADATA
jupyter_timetracker-0.0.3.dist-info/WHEEL
jupyter_timetracker-0.0.3.dist-info/top_level.txt
jupyter_timetracker-0.0.3.dist-info/RECORD
