Metadata-Version: 2.1
Name: jupyter-timetracker
Version: 0.0.3
Summary: jupyter-timetracker is a powerful python library to track, manage and analyse your time
Home-page: https://github.com/PrateekKumarPython/jupyter-timetracker
Author: Prateek Kumar
Author-email: prateekongithub@gmail.com
License: UNKNOWN
Platform: UNKNOWN
Classifier: Programming Language :: Python :: 3
Classifier: License :: OSI Approved :: BSD License
Classifier: Operating System :: OS Independent
Requires-Python: >=3.6
